sanic_limiter/__init__.py
sanic_limiter/errors.py
sanic_limiter/extension.py
sanic_limiter/util.py
sanic_limiter-0.1.3.dist-info/DESCRIPTION.rst
sanic_limiter-0.1.3.dist-info/METADATA
sanic_limiter-0.1.3.dist-info/RECORD
sanic_limiter-0.1.3.dist-info/WHEEL
sanic_limiter-0.1.3.dist-info/metadata.json
sanic_limiter-0.1.3.dist-info/top_level.txt
